README.md
setup.py
ast2vec/__init__.py
ast2vec/__main__.py
ast2vec/bblfsh_roles.py
ast2vec/bigartm.py
ast2vec/bow.py
ast2vec/cloning.py
ast2vec/coocc.py
ast2vec/df.py
ast2vec/dump.py
ast2vec/enry.py
ast2vec/id2vec.py
ast2vec/id_embedding.py
ast2vec/lazy_grpc.py
ast2vec/modelforgecfg.py
ast2vec/pickleable_logger.py
ast2vec/projector.py
ast2vec/resolve_symlink.py
ast2vec/source.py
ast2vec/swivel.py
ast2vec/token_parser.py
ast2vec/topics.py
ast2vec/uast.py
ast2vec/uast_ids_to_bag.py
ast2vec/voccoocc.py
ast2vec/vw_dataset.py
ast2vec.egg-info/PKG-INFO
ast2vec.egg-info/SOURCES.txt
ast2vec.egg-info/dependency_links.txt
ast2vec.egg-info/entry_points.txt
ast2vec.egg-info/requires.txt
ast2vec.egg-info/top_level.txt
ast2vec/model2/__init__.py
ast2vec/model2/base.py
ast2vec/model2/join_bow.py
ast2vec/model2/prox.py
ast2vec/model2/proxbase.py
ast2vec/model2/uast2bow.py
ast2vec/model2/uast2df.py
ast2vec/repo2/__init__.py
ast2vec/repo2/base.py
ast2vec/repo2/coocc.py
ast2vec/repo2/cooccbase.py
ast2vec/repo2/nbow.py
ast2vec/repo2/source.py
ast2vec/repo2/uast.py
ast2vec/repo2/voccoocc.py