Metadata-Version: 1.1
Name: ast2vec
Version: 0.3.7a0
Summary: Part of source{d}'s stack for machine learning on source code. Provides API and tools to train and use models based on source code identifiers extracted from Babelfish's UASTs.
Home-page: https://github.com/src-d/ast2vec
Author: source{d}
Author-email: machine-learning@sourced.tech
License: Apache 2.0
Download-URL: https://github.com/src-d/ast2vec
Keywords: machine learning on source code,word2vec,id2vec,github,swivel,nbow,bblfsh,babelfish
Platform: UNKNOWN
Classifier: Development Status :: 3 - Alpha
Classifier: Environment :: Console
Classifier: Intended Audience :: Developers
Classifier: License :: OSI Approved :: Apache Software License
Classifier: Operating System :: POSIX
Classifier: Programming Language :: Python :: 3.4
Classifier: Programming Language :: Python :: 3.5
Classifier: Programming Language :: Python :: 3.6
Classifier: Topic :: Software Development :: Libraries
